<annotation>
	<folder>肉</folder>
	<filename>DSC_1301.jpg</filename>
	<path>C:\Users\USER\Desktop\肉\DSC_1301.jpg</path>
	<source>
		<database>Unknown</database>
	</source>
	<size>
		<width>960</width>
		<height>540</height>
		<depth>3</depth>
	</size>
	<segmented>0</segmented>
	<object>
		<name>restructured meat</name>
		<pose>Unspecified</pose>
		<truncated>0</truncated>
		<difficult>0</difficult>
		<bndbox>
			<xmin>41</xmin>
			<ymin>6</ymin>
			<xmax>423</xmax>
			<ymax>163</ymax>
		</bndbox>
	</object>
	<object>
		<name>restructured meat</name>
		<pose>Unspecified</pose>
		<truncated>0</truncated>
		<difficult>0</difficult>
		<bndbox>
			<xmin>46</xmin>
			<ymin>187</ymin>
			<xmax>458</xmax>
			<ymax>521</ymax>
		</bndbox>
	</object>
	<object>
		<name>restructured meat</name>
		<pose>Unspecified</pose>
		<truncated>0</truncated>
		<difficult>0</difficult>
		<bndbox>
			<xmin>442</xmin>
			<ymin>41</ymin>
			<xmax>886</xmax>
			<ymax>379</ymax>
		</bndbox>
	</object>
</annotation>
