<annotation>
	<folder>training</folder>
	<filename>DSC_1705.jpg</filename>
	<path>C:\Users\user\Desktop\training\DSC_1705.jpg</path>
	<source>
		<database>Unknown</database>
	</source>
	<size>
		<width>960</width>
		<height>540</height>
		<depth>3</depth>
	</size>
	<segmented>0</segmented>
	<object>
		<name>restructured meat</name>
		<pose>Unspecified</pose>
		<truncated>0</truncated>
		<difficult>0</difficult>
		<bndbox>
			<xmin>409</xmin>
			<ymin>100</ymin>
			<xmax>588</xmax>
			<ymax>263</ymax>
		</bndbox>
	</object>
	<object>
		<name>restructured meat</name>
		<pose>Unspecified</pose>
		<truncated>1</truncated>
		<difficult>0</difficult>
		<bndbox>
			<xmin>1</xmin>
			<ymin>144</ymin>
			<xmax>191</xmax>
			<ymax>305</ymax>
		</bndbox>
	</object>
	<object>
		<name>restructured meat</name>
		<pose>Unspecified</pose>
		<truncated>0</truncated>
		<difficult>0</difficult>
		<bndbox>
			<xmin>776</xmin>
			<ymin>76</ymin>
			<xmax>917</xmax>
			<ymax>228</ymax>
		</bndbox>
	</object>
</annotation>
