<annotation>
	<folder>training</folder>
	<filename>DSC_1653.jpg</filename>
	<path>C:\Users\user\Desktop\training\DSC_1653.jpg</path>
	<source>
		<database>Unknown</database>
	</source>
	<size>
		<width>960</width>
		<height>540</height>
		<depth>3</depth>
	</size>
	<segmented>0</segmented>
	<object>
		<name>restructured meat</name>
		<pose>Unspecified</pose>
		<truncated>0</truncated>
		<difficult>0</difficult>
		<bndbox>
			<xmin>276</xmin>
			<ymin>20</ymin>
			<xmax>465</xmax>
			<ymax>202</ymax>
		</bndbox>
	</object>
	<object>
		<name>restructured meat</name>
		<pose>Unspecified</pose>
		<truncated>0</truncated>
		<difficult>0</difficult>
		<bndbox>
			<xmin>512</xmin>
			<ymin>5</ymin>
			<xmax>733</xmax>
			<ymax>182</ymax>
		</bndbox>
	</object>
	<object>
		<name>restructured meat</name>
		<pose>Unspecified</pose>
		<truncated>0</truncated>
		<difficult>0</difficult>
		<bndbox>
			<xmin>389</xmin>
			<ymin>195</ymin>
			<xmax>588</xmax>
			<ymax>389</ymax>
		</bndbox>
	</object>
	<object>
		<name>restructured meat</name>
		<pose>Unspecified</pose>
		<truncated>0</truncated>
		<difficult>0</difficult>
		<bndbox>
			<xmin>273</xmin>
			<ymin>341</ymin>
			<xmax>472</xmax>
			<ymax>535</ymax>
		</bndbox>
	</object>
	<object>
		<name>restructured meat</name>
		<pose>Unspecified</pose>
		<truncated>1</truncated>
		<difficult>0</difficult>
		<bndbox>
			<xmin>523</xmin>
			<ymin>346</ymin>
			<xmax>772</xmax>
			<ymax>540</ymax>
		</bndbox>
	</object>
</annotation>
