<annotation>
	<folder>肉</folder>
	<filename>DSC_1396.jpg</filename>
	<path>C:\Users\USER\Desktop\肉\DSC_1396.jpg</path>
	<source>
		<database>Unknown</database>
	</source>
	<size>
		<width>960</width>
		<height>540</height>
		<depth>3</depth>
	</size>
	<segmented>0</segmented>
	<object>
		<name>restructured meat</name>
		<pose>Unspecified</pose>
		<truncated>0</truncated>
		<difficult>0</difficult>
		<bndbox>
			<xmin>225</xmin>
			<ymin>64</ymin>
			<xmax>765</xmax>
			<ymax>525</ymax>
		</bndbox>
	</object>
	<object>
		<name>restructured meat</name>
		<pose>Unspecified</pose>
		<truncated>0</truncated>
		<difficult>0</difficult>
		<bndbox>
			<xmin>408</xmin>
			<ymin>2</ymin>
			<xmax>673</xmax>
			<ymax>56</ymax>
		</bndbox>
	</object>
</annotation>
